adafruit_lifx.py
adafruit_circuitpython_lifx-3.0.4.dist-info/licenses/LICENSE
adafruit_circuitpython_lifx-3.0.4.dist-info/METADATA
adafruit_circuitpython_lifx-3.0.4.dist-info/WHEEL
adafruit_circuitpython_lifx-3.0.4.dist-info/top_level.txt
adafruit_circuitpython_lifx-3.0.4.dist-info/RECORD
