Metadata-Version: 2.4
Name: adafruit-circuitpython-lifx
Version: 3.0.4
Summary: LIFX Smart Lighting API Helper
Author-email: Adafruit Industries <circuitpython@adafruit.com>
License: MIT
Project-URL: Homepage, https://github.com/adafruit/Adafruit_CircuitPython_lifx
Keywords: adafruit,blinka,circuitpython,micropython,lifx
Classifier: Intended Audience :: Developers
Classifier: Topic :: Software Development :: Libraries
Classifier: Topic :: Software Development :: Embedded Systems
Classifier: Topic :: System :: Hardware
Classifier: License :: OSI Approved :: MIT License
Classifier: Programming Language :: Python :: 3
License-File: LICENSE
Requires-Dist: Adafruit-Blinka
Requires-Dist: adafruit-circuitpython-typing~=1.8
Requires-Dist: adafruit-circuitpython-requests
Provides-Extra: optional
Dynamic: license-file
